{"namedChunkGroups":{"polyfill":{"name":"polyfill","assets":[{"name":"webpack-runtime-858cec4e9f08e5bde191.js","size":4062},{"name":"polyfill-e6b5355c9ecf751d8025.js","size":85302}],"filteredAssets":0,"assetsSize":89364,"filteredAuxiliaryAssets":2,"auxiliaryAssetsSize":223868},"app":{"name":"app","assets":[{"name":"webpack-runtime-858cec4e9f08e5bde191.js","size":4062},{"name":"framework-195c5a45ccc0b0805ce0.js","size":129935},{"name":"styles.2291949586241a071e14.css","size":8390},{"name":"app-80d5f4fa46e9a62bf90d.js","size":70482}],"filteredAssets":0,"assetsSize":212869,"filteredAuxiliaryAssets":3,"auxiliaryAssetsSize":661829},"component---src-pages-404-js":{"name":"component---src-pages-404-js","assets":[{"name":"commons-ab2410dfbec4227df496.js","size":16476},{"name":"component---src-pages-404-js-bb1698d01a7f9dde5caa.js","size":550}],"filteredAssets":0,"assetsSize":17026,"filteredAuxiliaryAssets":2,"auxiliaryAssetsSize":69432},"component---src-pages-index-js":{"name":"component---src-pages-index-js","assets":[{"name":"commons-ab2410dfbec4227df496.js","size":16476},{"name":"component---src-pages-index-js-f5d7cb8d004f01f8adc4.js","size":1760}],"filteredAssets":0,"assetsSize":18236,"filteredAuxiliaryAssets":2,"auxiliaryAssetsSize":73108},"component---src-pages-using-typescript-tsx":{"name":"component---src-pages-using-typescript-tsx","assets":[{"name":"commons-ab2410dfbec4227df496.js","size":16476},{"name":"component---src-pages-using-typescript-tsx-20f655bfb94bd369e9d3.js","size":1372}],"filteredAssets":0,"assetsSize":17848,"filteredAuxiliaryAssets":2,"auxiliaryAssetsSize":70528},"component---src-templates-blog-post-js":{"name":"component---src-templates-blog-post-js","assets":[{"name":"commons-ab2410dfbec4227df496.js","size":16476},{"name":"component---src-templates-blog-post-js-38361f037d9e46805408.js","size":1665}],"filteredAssets":0,"assetsSize":18141,"filteredAuxiliaryAssets":2,"auxiliaryAssetsSize":73356}},"assetsByChunkName":{"polyfill":["webpack-runtime-858cec4e9f08e5bde191.js","polyfill-e6b5355c9ecf751d8025.js"],"app":["webpack-runtime-858cec4e9f08e5bde191.js","framework-195c5a45ccc0b0805ce0.js","styles.2291949586241a071e14.css","app-80d5f4fa46e9a62bf90d.js"],"component---src-pages-404-js":["commons-ab2410dfbec4227df496.js","component---src-pages-404-js-bb1698d01a7f9dde5caa.js"],"component---src-pages-index-js":["commons-ab2410dfbec4227df496.js","component---src-pages-index-js-f5d7cb8d004f01f8adc4.js"],"component---src-pages-using-typescript-tsx":["commons-ab2410dfbec4227df496.js","component---src-pages-using-typescript-tsx-20f655bfb94bd369e9d3.js"],"component---src-templates-blog-post-js":["commons-ab2410dfbec4227df496.js","component---src-templates-blog-post-js-38361f037d9e46805408.js"]},"childAssetsByChunkName":{}}